public/__init__.py
public/block.py
public/canvas.py
public/functions.py
public/helpers/__init__.py
public/helpers/canvas_helpers.py
public/validation_configs/blocks.py
zerve_public-0.1.0.dist-info/METADATA
zerve_public-0.1.0.dist-info/WHEEL
zerve_public-0.1.0.dist-info/top_level.txt
zerve_public-0.1.0.dist-info/RECORD
