Metadata-Version: 2.1
Name: zerve-public
Version: 0.1.0
Summary: zerve's public python package
Author-email: "Zerve AI Ltd." <info@zerve.ai>
Requires-Python: >=3.6
Requires-Dist: jinja2>=3.1.3
Requires-Dist: registrable>=0.0.4
Requires-Dist: pydantic>=1.8.2
Requires-Dist: pandas>=2.0.2
Requires-Dist: polars>=0.18.0
Requires-Dist: pyarrow>=12.0.0
Requires-Dist: numpy>=1.23.4
Requires-Dist: matplotlib>=3.7.1
Requires-Dist: dill>=0.3.7
Requires-Dist: boto3>=1.18.62
Requires-Dist: azure-storage-blob>=12.17.0
Requires-Dist: google-cloud-storage>=2.10.0
Requires-Dist: mysql-connector-python>=8.0.27
Requires-Dist: sqlalchemy>=1.4.31
Requires-Dist: snowflake-connector-python>=3.1.0
Requires-Dist: psycopg2>=2.9.9
Requires-Dist: duckdb>=0.10.0
Requires-Dist: sql-metadata>=2.10.0
Requires-Dist: flit==3.8.0
Requires-Dist: flit-core==3.8.0
Requires-Dist: poetry==1.5.1
Requires-Dist: snowflake-snowpark-python==1.18.0
Requires-Dist: requests==2.32.3
Provides-Extra: dev
Requires-Dist: pylint~=2.14.0; extra == "dev"
Requires-Dist: toml~=0.10.2; extra == "dev"
Requires-Dist: yapf~=0.32.0; extra == "dev"
Provides-Extra: test
Requires-Dist: pytest-cov~=3.0.0; extra == "test"
Requires-Dist: pytest~=6.2.5; extra == "test"
